[
    {
        "name":"1. Strategik marketing (treyler)",
        "type":"video"
    },
    {
        "name":"2. SWOT analiz qilish",
        "type":"video"
    },
    {
        "name":"3. Ish muhiti",
        "type":"video"
    },
    {
        "name":"4. Biznesda politika qanday...",
        "type":"video"
    },
    {
        "name":"5. Bir burun qoydasi",
        "type":"video"
    },
    {
        "name":"SWOT dokument",
        "type":"doc"
    },
    {
        "name":"7. Fundamental marketing",
        "type":"video"
    },
    {
        "name":"8. Mijozlarimizning umrlik qiymati.",
        "type":"video"
    }
]